kago_utils/__init__.py
kago_utils/agari_calculator.py
kago_utils/bot.py
kago_utils/game.py
kago_utils/hai.py
kago_utils/hai_group.py
kago_utils/kawa.py
kago_utils/player.py
kago_utils/py.typed
kago_utils/shanten.py
kago_utils/tehai_decomposer.py
kago_utils/yama.py
kago_utils/zaichi.py
kago_utils/actions/__init__.py
kago_utils/actions/ankan.py
kago_utils/actions/chii.py
kago_utils/actions/dahai.py
kago_utils/actions/daiminkan.py
kago_utils/actions/kakan.py
kago_utils/actions/kyuushu_kyuuhai.py
kago_utils/actions/pon.py
kago_utils/actions/riichi.py
kago_utils/actions/ronho.py
kago_utils/actions/skip.py
kago_utils/actions/tsumoho.py
kago_utils/ext/__init__.py
kago_utils/ext/_shanten.c
kago_utils/ext/_shanten.cpython-312-x86_64-linux-gnu.so
kago_utils/ext/_shanten.pyi
kago_utils/resolvers/__init__.py
kago_utils/resolvers/chankan_action_resolver.py
kago_utils/resolvers/non_teban_action_resolver.py
kago_utils/resolvers/teban_action_resolver.py
kago_utils/resolvers/results/__init__.py
kago_utils/resolvers/results/ankan_result.py
kago_utils/resolvers/results/chii_result.py
kago_utils/resolvers/results/dahai_result.py
kago_utils/resolvers/results/daiminkan_result.py
kago_utils/resolvers/results/kakan_result.py
kago_utils/resolvers/results/kyuushu_kyuuhai_result.py
kago_utils/resolvers/results/pending.py
kago_utils/resolvers/results/pon_result.py
kago_utils/resolvers/results/riichi_result.py
kago_utils/resolvers/results/ronho_result.py
kago_utils/resolvers/results/skip_result.py
kago_utils/resolvers/results/tsumoho_result.py
kago_utils/resources/distance_tables/suuhai_distance_table.txt
kago_utils/resources/distance_tables/zihai_distance_table.txt
kago_utils/resources/images/0m-rotated.png
kago_utils/resources/images/0m.png
kago_utils/resources/images/0p-rotated.png
kago_utils/resources/images/0p.png
kago_utils/resources/images/0s-rotated.png
kago_utils/resources/images/0s.png
kago_utils/resources/images/1m-rotated.png
kago_utils-0.1.3.dist-info/METADATA
kago_utils-0.1.3.dist-info/WHEEL
kago_utils-0.1.3.dist-info/top_level.txt
kago_utils-0.1.3.dist-info/RECORD
kago_utils-0.1.3.dist-info/licenses/LICENSE
