Metadata-Version: 2.4
Name: kago-utils
Version: 0.1.3
Summary: Mahjong Library for Python
Author-email: zurukumo <zurukumo@gmail.com>
Project-URL: Homepage, https://github.com/zurukumo/kago-utils
Project-URL: Issues, https://github.com/zurukumo/kago-utils/issues
Classifier: Programming Language :: Python :: 3
Classifier: Intended Audience :: Developers
Classifier: License :: OSI Approved :: MIT License
Classifier: Operating System :: OS Independent
Classifier: Programming Language :: Python :: 3.12
Requires-Python: >=3.12
License-File: LICENSE
Dynamic: license-file
